raidtoolkit/Account.py
raidtoolkit/AccountApi.py
raidtoolkit/PromiseStore.py
raidtoolkit/RaidToolkit.py
raidtoolkit/RealtimeApi.py
raidtoolkit/RemoteApiClient.py
raidtoolkit/StaticDataApi.py
raidtoolkit/__init__.py
raidtoolkit-0.2.1.dist-info/LICENSE
raidtoolkit-0.2.1.dist-info/METADATA
raidtoolkit-0.2.1.dist-info/WHEEL
raidtoolkit-0.2.1.dist-info/top_level.txt
raidtoolkit-0.2.1.dist-info/RECORD
