Metadata-Version: 2.1
Name: raidtoolkit
Version: 0.2.1
Summary: Client for RaidToolkit API access
Home-page: https://github.com/raid-toolkit/raid-toolkit-sdk
Author: raid.toolkit
Author-email: raid.toolkit@gmail.com
Project-URL: Bug Tracker, https://github.com/raid-toolkit/raid-toolkit-sdk/issues
Classifier: Programming Language :: Python :: 3
Classifier: License :: OSI Approved :: MIT License
Classifier: Operating System :: OS Independent
Requires-Python: >=3.6
License-File: LICENSE
